{
  "ComponentIndexes": {},
  "ControlUniqueGuids": {},
  "ControlUniqueIds": {
    "App": 1,
    "Gallery1": 5,
    "Gallery2": 15,
    "galleryTemplate1": 6,
    "galleryTemplate2": 16,
    "Host": 3,
    "Image1": 8,
    "Image2": 17,
    "Label1": 13,
    "NextArrow1": 9,
    "NextArrow2": 20,
    "Rectangle1": 7,
    "Rectangle2": 22,
    "Screen1": 4,
    "Screen2": 14,
    "Separator1": 12,
    "Separator2": 21,
    "Subtitle1": 11,
    "Subtitle2": 19,
    "Title1": 10,
    "Title2": 18
  },
  "FunctionParamsInvariantScripts": {},
  "FunctionParamsInvariantScriptsOnInstances": {},
  "HeaderLastSavedDateTimeUTC": "02/06/2024 11:09:47",
  "IsLegacyComponentAllowGlobalScopeCase": false,
  "LocalConnectionIDReferences": {},
  "LocalDatabaseReferencesAsEmpty": false,
  "LocalResourceFileNames": {},
  "LocalResourceRootPaths": {},
  "OrderComponentMetadata": {},
  "OrderComponentTemplate": {},
  "OrderDataSource": {
    "CustomGallerySample": 9,
    "EmployeeLocation": 8,
    "EmployeeLocation\\brsk_employeelocation_statecode": 0,
    "EmployeeLocation\\brsk_employeelocation_statuscode": 1,
    "EmployeeLocation\\default.cds_brsk_employeelocation_views": 6,
    "Locations": 10,
    "Locations\\brsk_location_brsk_isdisplay": 2,
    "Locations\\brsk_location_statecode": 4,
    "Locations\\brsk_location_statuscode": 5,
    "Locations\\cr3e0_locationname": 3,
    "Locations\\default.cds_brsk_location_views": 7
  },
  "OrderGroupControls": {},
  "OrderPcfTemplate": {},
  "OrderTemplate": {},
  "OrderXMLTemplate": {
    "gallery": 0,
    "icon": 3,
    "image": 2,
    "label": 4,
    "rectangle": 1
  },
  "OverridablePropertiesEntry": {
    "App": {},
    "Gallery1": {},
    "Gallery2": {},
    "galleryTemplate1": {},
    "galleryTemplate2": {},
    "Host": {},
    "Image1": {},
    "Image2": {},
    "Label1": {},
    "NextArrow1": {},
    "NextArrow2": {},
    "Rectangle1": {},
    "Rectangle2": {},
    "Screen1": {},
    "Screen2": {},
    "Separator1": {},
    "Separator2": {},
    "Subtitle1": {},
    "Subtitle2": {},
    "Title1": {},
    "Title2": {}
  },
  "PCFDynamicSchemaForIRRetrievalEntry": {},
  "PCFTemplateEntry": {},
  "PublishOrderIndices": {
    "App": 0,
    "Gallery1": 0,
    "Gallery2": 0,
    "galleryTemplate1": 1,
    "galleryTemplate2": 0,
    "Host": 0,
    "Image1": 3,
    "Image2": 0,
    "Label1": 8,
    "NextArrow1": 4,
    "NextArrow2": 0,
    "Rectangle1": 2,
    "Rectangle2": 0,
    "Screen1": 0,
    "Screen2": 0,
    "Separator1": 7,
    "Separator2": 0,
    "Subtitle1": 6,
    "Subtitle2": 0,
    "Title1": 5,
    "Title2": 0
  },
  "ResourcesJsonIndices": {
    "Image-SampleImage": 0
  },
  "RuleScreenIdWithoutScreen": {},
  "TemplateVersions": {},
  "VolatileProperties": {
    "AnalysisLoadTime": 0.1151728,
    "ControlCount": {
      "gallery": 1,
      "galleryTemplate": 1,
      "icon": 1,
      "image": 1,
      "label": 3,
      "rectangle": 2,
      "screen": 1
    },
    "DeserializationLoadTime": 0.8914744
  },
  "WasLocalDatabaseReferencesEmpty": false
}